{
  "type": "minecraft:random_patch",
  "config": {
    "xz_spread": 1,
    "y_spread": 40,
    "feature": {
      "feature": {
        "type": "minecraft:geode",
        "config": {
          "blocks": {
            "filling_provider": {
              "type": "minecraft:simple_state_provider",
              "state": {
                "Name": "minecraft:air"
              }
            },
            "inner_layer_provider": {
              "type": "minecraft:simple_state_provider",
              "state": {
                "Name": "minecraft:air"
              }
            },
            "alternate_inner_layer_provider": {
              "type": "minecraft:simple_state_provider",
              "state": {
                "Name": "minecraft:air"
              }
            },
            "middle_layer_provider": {
              "type": "minecraft:simple_state_provider",
              "state": {
                "Name": "minecraft:air"
              }
            },
            "outer_layer_provider": {
              "type": "minecraft:simple_state_provider",
              "state": {
                "Name": "minecraft:air"
              }
            },
            "inner_placements": [
              {
                "Name": "minecraft:air"
              }
            ],
            "cannot_replace": "#verse:tag",
            "invalid_blocks": "#verse:tag"
          },
          "layers": {},
          "crack": {},
          "invalid_blocks_threshold": 1,
          "use_alternate_layer0_chance": 0.083
        }
      },
      "placement": [
        {
          "type": "minecraft:random_offset",
          "xz_spread": {
            "type": "uniform",
            "min_inclusive": -1,
            "max_inclusive": 1
          },
          "y_spread": -15
        }
      ]
    }
  }
}